CHANGES.txt
COPYRIGHT.txt
LICENSE.txt
README.txt
buildout.cfg
setup.py
scripts/generate
scripts/sources.list
van/__init__.py
van.pydeb.egg-info/PKG-INFO
van.pydeb.egg-info/SOURCES.txt
van.pydeb.egg-info/dependency_links.txt
van.pydeb.egg-info/entry_points.txt
van.pydeb.egg-info/namespace_packages.txt
van.pydeb.egg-info/not-zip-safe
van.pydeb.egg-info/requires.txt
van.pydeb.egg-info/top_level.txt
van/pydeb/__init__.py
van/pydeb/py_to_bin.txt
van/pydeb/py_to_src.txt
van/pydeb/tests/__init__.py
van/pydeb/tests/extras.txt
van/pydeb/tests/test_doctest.py
van/pydeb/tests/translations.txt
van/pydeb/tests/version.txt
van/pydeb/tests/dummy.FOO2.egg-info/PKG-INFO
van/pydeb/tests/dummy.FOO2.egg-info/SOURCES.txt
van/pydeb/tests/dummy.FOO2.egg-info/dependency_links.txt
van/pydeb/tests/dummy.FOO2.egg-info/namespace_packages.txt
van/pydeb/tests/dummy.FOO2.egg-info/requires.txt
van/pydeb/tests/dummy.FOO2.egg-info/top_level.txt
van/pydeb/tests/dummy.foo.egg-info/PKG-INFO
van/pydeb/tests/dummy.foo.egg-info/SOURCES.txt
van/pydeb/tests/dummy.foo.egg-info/dependency_links.txt
van/pydeb/tests/dummy.foo.egg-info/namespace_packages.txt
van/pydeb/tests/dummy.foo.egg-info/requires.txt
van/pydeb/tests/dummy.foo.egg-info/top_level.txt
van/pydeb/tests/zope.app.publication.egg-info/PKG-INFO
van/pydeb/tests/zope.app.publication.egg-info/SOURCES.txt
van/pydeb/tests/zope.app.publication.egg-info/dependency_links.txt
van/pydeb/tests/zope.app.publication.egg-info/namespace_packages.txt
van/pydeb/tests/zope.app.publication.egg-info/not-zip-safe
van/pydeb/tests/zope.app.publication.egg-info/requires.txt
van/pydeb/tests/zope.app.publication.egg-info/top_level.txt
van/pydeb/tests/zope.component.egg-info/PKG-INFO
van/pydeb/tests/zope.component.egg-info/SOURCES.txt
van/pydeb/tests/zope.component.egg-info/dependency_links.txt
van/pydeb/tests/zope.component.egg-info/namespace_packages.txt
van/pydeb/tests/zope.component.egg-info/not-zip-safe
van/pydeb/tests/zope.component.egg-info/requires.txt
van/pydeb/tests/zope.component.egg-info/top_level.txt
van/pydeb/tests/zope.security.egg-info/PKG-INFO
van/pydeb/tests/zope.security.egg-info/SOURCES.txt
van/pydeb/tests/zope.security.egg-info/dependency_links.txt
van/pydeb/tests/zope.security.egg-info/namespace_packages.txt
van/pydeb/tests/zope.security.egg-info/not-zip-safe
van/pydeb/tests/zope.security.egg-info/requires.txt
van/pydeb/tests/zope.security.egg-info/top_level.txt