Metadata-Version: 1.0
Name: van.pydeb
Version: 1.3.3
Summary: Make egg metadata information available for Debian packaging
Home-page: http://pypi.python.org/pypi/van.pydeb
Author: Vanguardistas
Author-email: UNKNOWN
License: ZPL 2.1
Platform: UNKNOWN
Classifier: Development Status :: 4 - Beta
Classifier: Intended Audience :: Developers
Classifier: Intended Audience :: System Administrators
Classifier: Topic :: System :: Archiving :: Packaging
Classifier: License :: DFSG approved
Classifier: License :: OSI Approved :: Zope Public License
Classifier: Framework :: Setuptools Plugin
Classifier: Operating System :: POSIX :: Linux
Classifier: Programming Language :: Python
